arxivabscraper/__init__.py
arxivabscraper/arxivabscraper.py
arxivabscraper-0.3.dist-info/LICENSE
arxivabscraper-0.3.dist-info/METADATA
arxivabscraper-0.3.dist-info/WHEEL
arxivabscraper-0.3.dist-info/top_level.txt
arxivabscraper-0.3.dist-info/RECORD
