Metadata-Version: 2.1
Name: arxivabscraper
Version: 0.3
Summary: Get arXiv.org abstracts within a date range and category
Home-page: https://github.com/MohamedElashri/Arxiv-Aabstract-scraper
Author: Mohamed Elashri
Author-email: muhammadelashri@gmail.com
License: MIT
Download-URL: https://github.com/MohamedElashri/Arxiv-Aabstract-scraper/archive/0.2.tar.gz
Keywords: arxiv,scraper,api,citation
Platform: UNKNOWN
Classifier: Programming Language :: Python :: 2
Classifier: Programming Language :: Python :: 2.7
Classifier: Programming Language :: Python :: 3
Classifier: Programming Language :: Python :: 3.8
Classifier: Operating System :: OS Independent
Classifier: Development Status :: 5 - Production/Stable
Classifier: Intended Audience :: Science/Research
Classifier: Topic :: Text Processing :: Markup :: LaTeX
